cvc5/__init__.py
cvc5/cvc5_python_base.cpython-313-x86_64-linux-gnu.so
cvc5/pythonic/__init__.py
cvc5/pythonic/cvc5_pythonic.py
cvc5/pythonic/cvc5_pythonic_printer.py
cvc5.libs/libcvc5-0e4dc5bf.so.1
cvc5.libs/libcvc5parser-b886ee8e.so.1
cvc5.libs/libgmp-97ca9d68.so.10.5.0
cvc5.libs/libpoly-3e3c501f.so.0.2.0
cvc5.libs/libpolyxx-c2a1a955.so.0.2.0
cvc5-1.3.2.dist-info/METADATA
cvc5-1.3.2.dist-info/WHEEL
cvc5-1.3.2.dist-info/top_level.txt
cvc5-1.3.2.dist-info/RECORD
cvc5-1.3.2.dist-info/licenses/COPYING
cvc5-1.3.2.dist-info/licenses/licenses/GCC-exception-3.1.txt
cvc5-1.3.2.dist-info/licenses/licenses/apache-2.0-with-llvm-exceptions.txt
cvc5-1.3.2.dist-info/licenses/licenses/gpl-3.0.txt
cvc5-1.3.2.dist-info/licenses/licenses/lgpl-3.0.txt
cvc5-1.3.2.dist-info/licenses/licenses/minisat-LICENSE
cvc5-1.3.2.dist-info/licenses/licenses/pythonic-LICENSE
